rlgym_learn-1.0.5.dist-info/METADATA
rlgym_learn-1.0.5.dist-info/WHEEL
rlgym_learn-1.0.5.dist-info/licenses/LICENSE
rlgym_learn/__init__.py
rlgym_learn/agent/__init__.py
rlgym_learn/agent/agent_manager.py
rlgym_learn/api/__init__.py
rlgym_learn/api/agent_controller.py
rlgym_learn/api/typing.py
rlgym_learn/env_processing/__init__.py
rlgym_learn/env_processing/env_process.py
rlgym_learn/env_processing/env_process_interface.py
rlgym_learn/learning_coordinator.py
rlgym_learn/learning_coordinator_config.py
rlgym_learn/py.typed
rlgym_learn/rlgym_learn.cpython-311-powerpc64le-linux-gnu.so
rlgym_learn/rlgym_learn.pyi
rlgym_learn/rocket_league/__init__.py
rlgym_learn/util/__init__.py
rlgym_learn/util/kbhit.py
rlgym_learn-1.0.5.dist-info/RECORD
