Metadata-Version: 2.4
Name: rlgym-learn
Version: 1.0.5
Classifier: Programming Language :: Rust
Classifier: Programming Language :: Python :: Implementation :: CPython
Requires-Dist: rlgym>=2.0.0
Requires-Dist: pydantic>=2.8.2
Requires-Dist: typing-extensions>4.6
Requires-Dist: rlgym[rl]>=2.0.0 ; extra == 'rl'
Requires-Dist: numpy>1.21 ; extra == 'rl'
Requires-Dist: torch>1.13 ; extra == 'tensor'
Provides-Extra: rl
Provides-Extra: tensor
License-File: LICENSE
Summary: A generic framework for using learning algorithms with effecient parallelization of RLGym environments and an ergonomic API
Author: Jonathan Keegan
License: Apache-2.0
Requires-Python: >=3.8, <3.14
